yaretry/__init__.py
yaretry/retry.py
yaretry-0.1.1.dist-info/DESCRIPTION.rst
yaretry-0.1.1.dist-info/METADATA
yaretry-0.1.1.dist-info/RECORD
yaretry-0.1.1.dist-info/WHEEL
yaretry-0.1.1.dist-info/metadata.json
yaretry-0.1.1.dist-info/top_level.txt
