Metadata-Version: 2.0
Name: yaretry
Version: 0.1.1
Summary: Small library for a neat looking retry wrapper
Home-page: https://github.com/Aloomaio/yaretry
Author: Rami Amar
Author-email: rami@alooma.com
License: UNKNOWN
Keywords: alooma, retry
Platform: UNKNOWN
Classifier: Programming Language :: Python :: 3
Classifier: Programming Language :: Python :: 2
Classifier: License :: OSI Approved :: Apache Software License
Classifier: Operating System :: OS Independent
